[
	{
		"inputs": [],
		"name": "claimToken",
		"outputs": [
			{
				"internalType": "bool",
				"name": "",
				"type": "bool"
			}
		],
		"stateMutability": "nonpayable",
		"type": "function"
	},
	{
		"inputs": [],
		"stateMutability": "nonpayable",
		"type": "constructor"
	},
	{
		"inputs": [],
		"name": "NotOwner",
		"type": "error"
	},
	{
		"inputs": [],
		"name": "resetMapping",
		"outputs": [],
		"stateMutability": "nonpayable",
		"type": "function"
	},
	{
		"inputs": [],
		"name": "SelectNull",
		"type": "error"
	},
	{
		"anonymous": false,
		"inputs": [
			{
				"indexed": true,
				"internalType": "address",
				"name": "_to",
				"type": "address"
			},
			{
				"indexed": false,
				"internalType": "uint256",
				"name": "_amount",
				"type": "uint256"
			}
		],
		"name": "SendRecord",
		"type": "event"
	},
	{
		"inputs": [
			{
				"internalType": "address",
				"name": "_token",
				"type": "address"
			}
		],
		"name": "setToken",
		"outputs": [],
		"stateMutability": "nonpayable",
		"type": "function"
	},
	{
		"inputs": [
			{
				"internalType": "address",
				"name": "_address",
				"type": "address"
			},
			{
				"internalType": "uint256",
				"name": "_amount",
				"type": "uint256"
			},
			{
				"internalType": "bool",
				"name": "_isClaim",
				"type": "bool"
			}
		],
		"name": "setUserMap",
		"outputs": [],
		"stateMutability": "nonpayable",
		"type": "function"
	},
	{
		"inputs": [
			{
				"internalType": "address",
				"name": "_to",
				"type": "address"
			},
			{
				"internalType": "uint256",
				"name": "_amount",
				"type": "uint256"
			}
		],
		"name": "withdraw",
		"outputs": [],
		"stateMutability": "nonpayable",
		"type": "function"
	},
	{
		"inputs": [],
		"name": "getTokenBalance",
		"outputs": [
			{
				"internalType": "uint256",
				"name": "",
				"type": "uint256"
			}
		],
		"stateMutability": "view",
		"type": "function"
	},
	{
		"inputs": [],
		"name": "getUserKey",
		"outputs": [
			{
				"internalType": "address[]",
				"name": "",
				"type": "address[]"
			}
		],
		"stateMutability": "view",
		"type": "function"
	},
	{
		"inputs": [],
		"name": "getUserLength",
		"outputs": [
			{
				"internalType": "uint256",
				"name": "",
				"type": "uint256"
			}
		],
		"stateMutability": "view",
		"type": "function"
	},
	{
		"inputs": [],
		"name": "i_owner",
		"outputs": [
			{
				"internalType": "address",
				"name": "",
				"type": "address"
			}
		],
		"stateMutability": "view",
		"type": "function"
	},
	{
		"inputs": [
			{
				"internalType": "uint256",
				"name": "",
				"type": "uint256"
			}
		],
		"name": "keys",
		"outputs": [
			{
				"internalType": "address",
				"name": "",
				"type": "address"
			}
		],
		"stateMutability": "view",
		"type": "function"
	},
	{
		"inputs": [
			{
				"internalType": "address",
				"name": "",
				"type": "address"
			}
		],
		"name": "userMap",
		"outputs": [
			{
				"internalType": "uint256",
				"name": "amount",
				"type": "uint256"
			},
			{
				"internalType": "bool",
				"name": "isClaim",
				"type": "bool"
			}
		],
		"stateMutability": "view",
		"type": "function"
	}
]